{
    "id": "tweet-2",
    "value": "Template 7 - text, profile image",
    "template": "<div class=\"container twitter-container \">\n<div class=\"twitter-col col-12\">\n<div class=\"twitter-col col-2 img-container\">[ProfileImage|bigger]</div>\n\n<div class=\"twitter-col col-10\">\n<div class=\"name\">[User]</div>\n\n<div class=\"username\">[ScreenName]</div>\n</div>\n</div>\n\n<div class=\"twitter-col col-12 \">\n<div class=\"main-tweet\">[Tweet]</div>\n\n<div class=\"twitter-col col-3 twitter-date\">[Date]</div>\n\n<div class=\"twitter-col col-9 twitter-location text-right \">[Location]</div>\n</div>\n</div>\n",
    "css": ".item {\n    float: left;\n}\n\nbody {\n    font-family: \"Helvetica\", \"Arial\", sans-serif;\n    line-height: 1;\n    background-repeat: no-repeat;\n    background-size: cover;\n    background-position: center;\n}\n\n.twitter-container {\n    padding-top: 30px;\n    width: 600px !important;\n    height: 460px !important;\n    padding-bottom: 40px;\n    background-color: rgba(255, 255, 255, 0.6);\n    background: rgba(255, 255, 255, 0.6);\n    color: rgba(255, 255, 255, 0.6);\n}\n\n.img-container img {\n    width: 80px;\n    height: 80px;\n    border: 3px solid #fff;\n}\n\n.main-tweet {\n    font-size: 35px;\n    padding-top: 30px;\n    line-height: 130%;\n    color: #434343;\n    height: 280px;\n}\n\n.emojione {\n    width: 30px;\n    height: 30px\n}\n\n.twitter-date, .twitter-location {\n    margin-top: 30px;\n    font-size: 17px;\n    color: #434343;\n    font-weight: bold;\n}\n\n.name {\n    font-size: 25px;\n    font-weight: bold;\n    color: #434343;\n    margin-top: 5px;\n}\n\n.username {\n    margin-top: 5px;\n    color: #434343;\n}\n\n.avatar {\n    border: 3px solid #fff;\n}\n\n.row {\n    margin-right: -15px;\n    margin-left: -15px;\n}\n\n.col-2 {\n    width: 16.66666667%;\n}\n\n.col-3 {\n    width: 25%;\n}\n\n.col-9 {\n    width: 75%;\n}\n\n.col-10 {\n    width: 83.33333333%;\n}\n\n.col-12 {\n    width: 100%;\n}\n\n.twitter-col {\n    float: left;\n    position: relative;\n    min-height: 1px;\n    padding-right: 15px;\n    padding-left: 15px;\n}",
    "widgetOriginalWidth": "600",
    "widgetOriginalHeight": "460",
    "widgetOriginalPadding": "20",
    "resultContent": "1",
    "image":"modules/twitter/template-thumbs/twitter2.png",
    "defaultVisualEditor": false
}